MANIFEST.in
README.rst
setup.py
./pyelevator/__init__.py
./pyelevator/base.py
./pyelevator/batch.py
./pyelevator/client.py
./pyelevator/constants.py
./pyelevator/error.py
./pyelevator/message.py
./pyelevator/utils/__init__.py
./pyelevator/utils/patterns.py
./pyelevator/utils/snippets.py
docs/Makefile
py_elevator.egg-info/PKG-INFO
py_elevator.egg-info/SOURCES.txt
py_elevator.egg-info/dependency_links.txt
py_elevator.egg-info/requires.txt
py_elevator.egg-info/top_level.txt
tests/__init__.py
tests/__init__.pyc
tests/elevator_test.py
tests/elevator_test.pyc
tests/fakers.py
tests/fakers.pyc
tests/message_test.py
tests/message_test.pyc
tests/untitled
tests/writebatch_test.py
tests/writebatch_test.pyc