Metadata-Version: 1.0
Name: py-elevator
Version: 0.5c
Summary: Python client for on-disk key/value database Elevator
Home-page: http://github.com/oleiade/py-elevator
Author: Oleiade
Author-email: tcrevon@gmail.com
License: MIT
Keywords: py-elevator elevator leveldb database key-value
Platform: UNKNOWN
Classifier: Development Status :: 5 - Production/Stable
Classifier: Programming Language :: Python :: 2.7
Classifier: License :: OSI Approved :: MIT License
Classifier: Operating System :: Unix
